ros_shape_msgs-5.5.1.data/data/include/shape_msgs/shape_msgs/msg/mesh.h
ros_shape_msgs-5.5.1.data/data/include/shape_msgs/shape_msgs/msg/mesh.hpp
ros_shape_msgs-5.5.1.data/data/include/shape_msgs/shape_msgs/msg/mesh_triangle.h
ros_shape_msgs-5.5.1.data/data/include/shape_msgs/shape_msgs/msg/mesh_triangle.hpp
ros_shape_msgs-5.5.1.data/data/include/shape_msgs/shape_msgs/msg/plane.h
ros_shape_msgs-5.5.1.data/data/include/shape_msgs/shape_msgs/msg/plane.hpp
ros_shape_msgs-5.5.1.data/data/include/shape_msgs/shape_msgs/msg/rosidl_generator_c__visibility_control.h
ros_shape_msgs-5.5.1.data/data/include/shape_msgs/shape_msgs/msg/rosidl_generator_cpp__visibility_control.hpp
ros_shape_msgs-5.5.1.data/data/include/shape_msgs/shape_msgs/msg/rosidl_typesupport_fastrtps_c__visibility_control.h
ros_shape_msgs-5.5.1.data/data/include/shape_msgs/shape_msgs/msg/rosidl_typesupport_fastrtps_cpp__visibility_control.h
ros_shape_msgs-5.5.1.data/data/include/shape_msgs/shape_msgs/msg/rosidl_typesupport_introspection_c__visibility_control.h
ros_shape_msgs-5.5.1.data/data/include/shape_msgs/shape_msgs/msg/solid_primitive.h
ros_shape_msgs-5.5.1.data/data/include/shape_msgs/shape_msgs/msg/solid_primitive.hpp
ros_shape_msgs-5.5.1.data/data/include/shape_msgs/shape_msgs/msg/detail/mesh__builder.hpp
ros_shape_msgs-5.5.1.data/data/include/shape_msgs/shape_msgs/msg/detail/mesh__description.c
ros_shape_msgs-5.5.1.data/data/include/shape_msgs/shape_msgs/msg/detail/mesh__functions.c
ros_shape_msgs-5.5.1.data/data/include/shape_msgs/shape_msgs/msg/detail/mesh__functions.h
ros_shape_msgs-5.5.1.data/data/include/shape_msgs/shape_msgs/msg/detail/mesh__rosidl_typesupport_fastrtps_c.h
ros_shape_msgs-5.5.1.data/data/include/shape_msgs/shape_msgs/msg/detail/mesh__rosidl_typesupport_fastrtps_cpp.hpp
ros_shape_msgs-5.5.1.data/data/include/shape_msgs/shape_msgs/msg/detail/mesh__rosidl_typesupport_introspection_c.h
ros_shape_msgs-5.5.1.data/data/lib/python3.10/site-packages/shape_msgs-5.5.1-py3.10.egg-info/PKG-INFO
ros_shape_msgs-5.5.1.data/data/lib/python3.10/site-packages/shape_msgs-5.5.1-py3.10.egg-info/SOURCES.txt
ros_shape_msgs-5.5.1.data/data/lib/python3.10/site-packages/shape_msgs-5.5.1-py3.10.egg-info/dependency_links.txt
ros_shape_msgs-5.5.1.data/data/lib/python3.10/site-packages/shape_msgs-5.5.1-py3.10.egg-info/top_level.txt
ros_shape_msgs-5.5.1.dist-info/METADATA
ros_shape_msgs-5.5.1.dist-info/WHEEL
ros_shape_msgs-5.5.1.dist-info/top_level.txt
ros_shape_msgs-5.5.1.dist-info/RECORD
ros_shape_msgs-5.5.1.dist-info/licenses/LICENSE
