Metadata-Version: 2.4
Name: ros-shape-msgs
Version: 5.5.1
Summary: ROS package `shape_msgs` provides standard messages for describing 3D shapes like meshes, planes, and solid primitives.
License-File: LICENSE
Requires-Dist: ros-geometry-msgs~=5.5.1
Requires-Dist: ros-rosidl-default-runtime~=1.7.1
Dynamic: description
Dynamic: description-content-type
Dynamic: license-file
Dynamic: requires-dist
Dynamic: summary
